fagroupa
