Metadata-Version: 1.0
Name: fagroupa
Version: 0.25
Summary: Try many sklearn algorithms in no time!
Home-page: https://github.com/martinmaseda/fagroupa
Author: Ivan Martin Maseda
Author-email: ivan.martin@student.ie.edu
License: MIT
Platform: UNKNOWN
